README.txt
setup.cfg
setup.py
FightForNetNeutrality.egg-info/PKG-INFO
FightForNetNeutrality.egg-info/SOURCES.txt
FightForNetNeutrality.egg-info/dependency_links.txt
FightForNetNeutrality.egg-info/entry_points.txt
FightForNetNeutrality.egg-info/not-zip-safe
FightForNetNeutrality.egg-info/top_level.txt
fightfornetneutrality/__init__.py
fightfornetneutrality/tests.py