Metadata-Version: 1.0
Name: FightForNetNeutrality
Version: 0.1
Summary: This package is a WSGI middleware which allow to block some IP Address. By default the french parlement is denied.
Home-page: http://reflets.info/wp-neutalityfr-la-neutralite-du-net-expliquee-de-maniere-optimalisee-a-muriel/
Author: Gael Pasgrimaud
Author-email: gael@gawel.org
License: GPL
Keywords: net neutrality wsgi
Platform: UNKNOWN
